{
"type": "FeatureCollection",
"name": "P_Lumti to Gharurhi, Mankot1",
"crs": { "type": "name", "properties": { "name": "urn:ogc:def:crs:OGC:1.3:CRS84" } },
"features": [
{ "type": "Feature", "properties": { "Name": "D.Y-1", "description": null, "timestamp": null, "begin": null, "end": null, "altitudeMode": null, "tessellate": -1, "extrude": 0, "visibility": 0, "drawOrder": null, "icon": null }, "geometry": { "type": "Point", "coordinates": [ 80.52206666666666, 30.28306666666667, 0.0 ] } },
{ "type": "Feature", "properties": { "Name": "D.Y-2", "description": null, "timestamp": null, "begin": null, "end": null, "altitudeMode": null, "tessellate": -1, "extrude": 0, "visibility": 0, "drawOrder": null, "icon": null }, "geometry": { "type": "Point", "coordinates": [ 80.5232, 30.2872, 0.0 ] } },
{ "type": "Feature", "properties": { "Name": "D.Y-3", "description": null, "timestamp": null, "begin": null, "end": null, "altitudeMode": null, "tessellate": -1, "extrude": 0, "visibility": 0, "drawOrder": null, "icon": null }, "geometry": { "type": "Point", "coordinates": [ 80.518433333333334, 30.292416666666671, 0.0 ] } },
{ "type": "Feature", "properties": { "Name": "D.Y-4", "description": null, "timestamp": null, "begin": null, "end": null, "altitudeMode": null, "tessellate": -1, "extrude": 0, "visibility": 0, "drawOrder": null, "icon": null }, "geometry": { "type": "Point", "coordinates": [ 80.5162, 30.297766666666671, 0.0 ] } },
{ "type": "Feature", "properties": { "Name": "D.Y-5", "description": null, "timestamp": null, "begin": null, "end": null, "altitudeMode": null, "tessellate": -1, "extrude": 0, "visibility": 0, "drawOrder": null, "icon": null }, "geometry": { "type": "Point", "coordinates": [ 80.512566666666672, 30.301066666666671, 0.0 ] } },
{ "type": "Feature", "properties": { "Name": "D.Y-6", "description": null, "timestamp": null, "begin": null, "end": null, "altitudeMode": null, "tessellate": -1, "extrude": 0, "visibility": 0, "drawOrder": null, "icon": null }, "geometry": { "type": "Point", "coordinates": [ 80.509566666666672, 30.303666666666668, 0.0 ] } },
{ "type": "Feature", "properties": { "Name": "D.Y-7", "description": null, "timestamp": null, "begin": null, "end": null, "altitudeMode": null, "tessellate": -1, "extrude": 0, "visibility": 0, "drawOrder": null, "icon": null }, "geometry": { "type": "Point", "coordinates": [ 80.498683333333332, 30.308716666666669, 0.0 ] } },
{ "type": "Feature", "properties": { "Name": "D.Y-8", "description": null, "timestamp": null, "begin": null, "end": null, "altitudeMode": null, "tessellate": -1, "extrude": 0, "visibility": 0, "drawOrder": null, "icon": null }, "geometry": { "type": "Point", "coordinates": [ 80.4933, 30.31141666666667, 0.0 ] } }
]
}
