{
"type": "FeatureCollection",
"name": "P_Narayan Ashram to Pasti Jaikot1",
"crs": { "type": "name", "properties": { "name": "urn:ogc:def:crs:OGC:1.3:CRS84" } },
"features": [
{ "type": "Feature", "properties": { "Name": "CA", "description": null, "timestamp": null, "begin": null, "end": null, "altitudeMode": null, "tessellate": -1, "extrude": 0, "visibility": 0, "drawOrder": null, "icon": null }, "geometry": { "type": "Point", "coordinates": [ 80.63621944444445, 29.985158333333331, 0.0 ] } }
]
}
